loadpup/__init__.py
loadpup/benchmark_base.py
loadpup/cli.py
loadpup/dify_benchmark.py
loadpup/main.py
loadpup/openai_benchmark.py
loadpup-1.0.0.dist-info/LICENSE
loadpup-1.0.0.dist-info/METADATA
loadpup-1.0.0.dist-info/WHEEL
loadpup-1.0.0.dist-info/RECORD
