Metadata-Version: 2.3
Name: loadpup
Version: 1.0.0
Summary: 专业的API性能压测工具，专门设计用于对大语言模型(LLM)API进行全面的性能测试和分析
License: Apache-2.0
Keywords: api,benchmark,performance,load-testing,llm,openai,dify
Author: LoadPup Team
Author-email: anon2010@163.com
Requires-Python: >=3.11,<4.0
Classifier: Development Status :: 5 - Production/Stable
Classifier: Intended Audience :: Developers
Classifier: License :: OSI Approved :: Apache Software License
Classifier: Operating System :: OS Independent
Classifier: Programming Language :: Python :: 3
Classifier: Programming Language :: Python :: 3.11
Classifier: Programming Language :: Python :: 3.12
Classifier: Programming Language :: Python :: 3.13
Classifier: Topic :: Software Development :: Testing
Classifier: Topic :: System :: Benchmark
Requires-Dist: aiohttp (>=3.8.0,<4.0.0)
Requires-Dist: evalscope (==0.16.1)
Requires-Dist: fastapi (==0.115.12)
Requires-Dist: numpy (>=1.20.0,<2.0.0)
Requires-Dist: openpyxl (>=3.1.5,<4.0.0)
Requires-Dist: pandas (>=2.0.0,<3.0.0)
Requires-Dist: requests (>=2.25.0,<3.0.0)
Requires-Dist: rich (>=13.9.4,<14.0.0)
Requires-Dist: sse_starlette (>=2.2.1,<3.0.0)
Requires-Dist: transformers (==4.48.3)
Requires-Dist: uvicorn (>=0.34.0,<0.35.0)
Project-URL: Documentation, https://github.com/anonNo2/LoadPup#readme
Project-URL: Homepage, https://github.com/anonNo2/LoadPup
Project-URL: Repository, https://github.com/anonNo2/LoadPup
